mtproto/__init__.py
mtproto/buffer.py
mtproto/connection.py
mtproto/crypto/__init__.py
mtproto/crypto/aes.py
mtproto/enums.py
mtproto/packets/__init__.py
mtproto/packets/base_packet.py
mtproto/packets/error_packet.py
mtproto/packets/message_packet.py
mtproto/packets/quick_ack_packet.py
mtproto/transports/__init__.py
mtproto/transports/abridged.py
mtproto/transports/base_transport.py
mtproto/transports/full.py
mtproto/transports/intermediate.py
mtproto/transports/obfuscated.py
mtproto/transports/padded_intermediate.py
mtproto/utils/__init__.py
mtproto/utils/auto_repr.py
mtproto/utils/tl_int.py
mtproto-0.1.2.dist-info/LICENSE
mtproto-0.1.2.dist-info/METADATA
mtproto-0.1.2.dist-info/WHEEL
mtproto-0.1.2.dist-info/RECORD
