Metadata-Version: 2.1
Name: mtproto
Version: 0.1.2
Summary: Telegram MTProto protocol implementation
License: MIT
Author: RuslanUC
Author-email: dev_ruslan_uc@protonmail.com
Requires-Python: >=3.9,<4.0
Classifier: Development Status :: 4 - Beta
Classifier: Intended Audience :: Developers
Classifier: License :: OSI Approved :: MIT License
Classifier: Operating System :: OS Independent
Classifier: Programming Language :: Python
Classifier: Programming Language :: Python :: 3
Classifier: Programming Language :: Python :: 3.9
Classifier: Programming Language :: Python :: 3.10
Classifier: Programming Language :: Python :: 3.11
Classifier: Programming Language :: Python :: 3.12
Classifier: Programming Language :: Python :: 3 :: Only
Classifier: Topic :: Internet
Classifier: Topic :: Utilities
Classifier: Typing :: Typed
Provides-Extra: pyaes
Provides-Extra: tgcrypto
Requires-Dist: pyaes (>=1.6.1,<2.0.0) ; extra == "pyaes"
Requires-Dist: tgcrypto (>=1.2.5,<2.0.0) ; extra == "tgcrypto"
Project-URL: Homepage, https://github.com/RuslanUC/mtproto
Project-URL: Repository, https://github.com/RuslanUC/mtproto
